upxlink/__init__.py
upxlink/__main__.py
upxlink/cli.py
upxlink/connection.py
upxlink/credentials.py
upxlink/interface.py
upxlink/ssl.py
upxlink/entities/__init__.py
upxlink/entities/chargingmanager.py
upxlink/entities/entities.py
upxlink-0.1.0.dist-info/METADATA
upxlink-0.1.0.dist-info/WHEEL
upxlink-0.1.0.dist-info/entry_points.txt
upxlink-0.1.0.dist-info/licenses/LICENCE
upxlink-0.1.0.dist-info/RECORD
