Metadata-Version: 2.4
Name: upxlink
Version: 0.1.0
Summary: Access the REST interface of VW up! and related cars
Project-URL: Homepage, https://github.com/hahnworks/upXlink
Project-URL: Issues, https://github.com/hahnworks/upXlink/issues
Author-email: Alexander Hahn <hahnworks@posteo.net>
License-Expression: EUPL-1.2
License-File: LICENCE
Classifier: License :: OSI Approved :: European Union Public Licence 1.2 (EUPL 1.2)
Classifier: Operating System :: OS Independent
Classifier: Programming Language :: Python :: 3.10
Classifier: Programming Language :: Python :: 3.11
Classifier: Programming Language :: Python :: 3.12
Classifier: Topic :: Software Development :: Libraries :: Python Modules
Classifier: Topic :: Utilities
Requires-Python: >=3.10
Requires-Dist: mibbridge>=0.1
Requires-Dist: requests
Provides-Extra: test
Requires-Dist: pytest; extra == 'test'
Requires-Dist: requests; extra == 'test'
